Flowsheet_Class/OntoCape_SFILES_mapping.py
Flowsheet_Class/__init__.py
Flowsheet_Class/flowsheet.py
Flowsheet_Class/nx_to_sfiles.py
Flowsheet_Class/utils_visualization.py
sfiles2-1.1.1.dist-info/METADATA
sfiles2-1.1.1.dist-info/WHEEL
sfiles2-1.1.1.dist-info/licenses/LICENSE
sfiles2-1.1.1.dist-info/RECORD
