Metadata-Version: 2.4
Name: SFILES2
Version: 1.1.1
Summary: Conversion between PFDs/P&IDs and SFILES 2.0 strings.
Project-URL: Homepage, https://www.pi-research.org/
Project-URL: Source, https://github.com/process-intelligence-research/SFILES2
Author-email: "Artur M. Schweidtmann" <A.Schweidtmann@tudelft.nl>, Gabriel Vogel <G.Vogel@tudelft.nl>, Edwin Hirtreiter <edwin.hirtreiter@tum.de>, Lukas Schulze Balhorn <L.Schulzebalhorn@tudelft.nl>
License-File: LICENSE
Keywords: SFILES 2.0, PFD, chemical engineering
Classifier: License :: OSI Approved :: MIT License
Classifier: Operating System :: OS Independent
Classifier: Programming Language :: Python :: 3
Requires-Python: >=3.9
Requires-Dist: ipykernel
Requires-Dist: ipython>=7.30.1
Requires-Dist: matplotlib>=3.8.4
Requires-Dist: networkx>=3.2.1
Requires-Dist: numpy>=2.1.3
Requires-Dist: pathfinding>=1.0.1
Requires-Dist: pyflowsheet>=0.2.2
Requires-Dist: tabulate>=0.8.9
